Metadata-Version: 2.4
Name: kiwitcms-tenants
Version: 4.4.1
Summary: Multi-tenant support for Kiwi TCMS
Home-page: https://github.com/kiwitcms/tenants/
Author: Kiwi TCMS
Author-email: info@kiwitcms.org
License: AGPLv3+
Classifier: Framework :: Django
Classifier: Development Status :: 5 - Production/Stable
Classifier: Topic :: Software Development :: Quality Assurance
Classifier: Topic :: Software Development :: Testing
Classifier: Environment :: Web Environment
Classifier: Intended Audience :: Developers
Classifier: License :: OSI Approved :: GNU Affero General Public License v3 or later (AGPLv3+)
Classifier: Programming Language :: Python :: 3
Classifier: Programming Language :: Python :: 3.8
Classifier: Programming Language :: Python :: 3.9
Classifier: Programming Language :: Python :: 3.11
License-File: LICENSE
Requires-Dist: kiwitcms-django-tenants==3.8.0
Requires-Dist: sqlparse>=0.5.0
Dynamic: author
Dynamic: author-email
Dynamic: classifier
Dynamic: description
Dynamic: home-page
Dynamic: license
Dynamic: license-file
Dynamic: requires-dist
Dynamic: summary
